AUTHOR
LICENSE
MANIFEST.in
README.md
VERSION
setup.py
gelid/__init__.py
gelid/settings.py
gelid.egg-info/PKG-INFO
gelid.egg-info/SOURCES.txt
gelid.egg-info/dependency_links.txt
gelid.egg-info/pbr.json
gelid.egg-info/requires.txt
gelid.egg-info/top_level.txt
gelid/extractors/__init__.py
gelid/extractors/content.py
gelid/extractors/decorator.py
gelid/extractors/enums.py
gelid/extractors/html.py
gelid/extractors/link.py
gelid/extractors/page.py
gelid/extractors/regex.py
gelid/extractors/scan.py
gelid/extractors/score.py
gelid/extractors/title.py
gelid/extractors/tm.py
gelid/extractors/xpath.py
gelid/items/__init__.py
gelid/items/article.py