Metadata-Version: 1.0
Name: gelid
Version: 1.5.5
Summary: gelid专注中文网页内容抽取
Home-page: https://github.com/lvjiyong/python-gelid
Author: lvjiyong
Author-email: lvjiyong@gmail.com
License: Apache2.0
Platform: any
